{
    "name": "grr_hunt_artifacts",
    "tags": ["grr", "hunt", "artifact"],
    "short_description": "Starts a GRR hunt for the default set of artifacts.",
    "description": "Starts a GRR artifact hunt and provides the Hunt ID to the user. Feed the Hunt ID to `grr_huntresults_ts` to process results through Plaso and export them to Timesketch.",
    "modules": [{
        "wants": [],
        "name": "GRRHuntArtifactCollector",
        "args": {
            "artifacts": "@artifacts",
            "reason": "@reason",
            "grr_server_url": "@grr_server_url",
            "grr_username": "@grr_username",
            "grr_password": "@grr_password",
            "max_file_size": "@max_file_size",
            "use_tsk": "@use_tsk",
            "approvers": "@approvers",
            "verify": "@verify"
        }
    }],
    "args": [
        ["artifacts", "Comma-separated list of artifacts to hunt for.", null],
        ["reason", "Reason for collection.", null],
        ["--use_tsk", "Use TSK to fetch artifacts.", false],
        ["--approvers", "Emails for GRR approval request.", null],
        ["--grr_server_url", "GRR endpoint", "http://localhost:8000"],
        ["--verify", "Whether to verify the GRR TLS certificate.", true],
        ["--grr_username", "GRR username", "admin"],
        ["--grr_password", "GRR password", "admin"],
        ["--max_file_size", "Maximum size of files to collect (in bytes).", 5368709120]
    ]
}
